centrometal_web_boiler/HttpClient.py
centrometal_web_boiler/HttpHelper.py
centrometal_web_boiler/WebBoilerClient.py
centrometal_web_boiler/WebBoilerDeviceCollection.py
centrometal_web_boiler/WebBoilerWsClient.py
centrometal_web_boiler/__init__.py
centrometal_web_boiler/const.py
centrometal_web_boiler/ws/__init__.py
centrometal_web_boiler/ws/base.py
centrometal_web_boiler/ws/client.py
centrometal_web_boiler/ws/collector.py
centrometal_web_boiler/ws/server.py
centrometal_web_boiler/ws/exceptions/__init__.py
centrometal_web_boiler/ws/exceptions/event.py
centrometal_web_boiler/ws/exceptions/parameter.py
centrometal_web_boiler/ws/models/__init__.py
centrometal_web_boiler/ws/models/data.py
centrometal_web_boiler/ws/models/message.py
centrometal_web_boiler/ws/utils/__init__.py
centrometal_web_boiler/ws/utils/converters.py
centrometal_web_boiler/ws/utils/typing_checking.py
centrometal_web_boiler/ws/wsprotocols/__init__.py
centrometal_web_boiler/ws/wsprotocols/client.py
centrometal_web_boiler/ws/wsprotocols/server.py
py_centrometal_web_boiler-0.0.58.dist-info/LICENSE
py_centrometal_web_boiler-0.0.58.dist-info/METADATA
py_centrometal_web_boiler-0.0.58.dist-info/WHEEL
py_centrometal_web_boiler-0.0.58.dist-info/top_level.txt
py_centrometal_web_boiler-0.0.58.dist-info/RECORD
