Metadata-Version: 2.1
Name: py-centrometal-web-boiler
Version: 0.0.58
Summary: Python library to interact with Centrometal Boiler System.
Home-page: https://github.com/9a4gl/py-centrometal-web-boiler
Author: Tihomir Heidelberg
Author-email: tihomir.heidelberg@lite.hr
Project-URL: Bug Tracker, https://github.com/9a4gl/py-centrometal-web-boiler/issues
Classifier: Programming Language :: Python :: 3
Classifier: License :: OSI Approved :: Apache Software License
Classifier: Operating System :: OS Independent
Requires-Python: >=3.6
License-File: LICENSE
Requires-Dist: lxml>=4.9.1
Requires-Dist: websockets>=10.3
Requires-Dist: stomper>=0.4.3
Requires-Dist: aiohttp>=3.8.1
Requires-Dist: faust-cchardet>=2.1.8
Requires-Dist: aiodns>=3.0.0
